{"_type":"export","__export_format":4,"__export_date":"2022-02-16T05:47:31.715Z","__export_source":"insomnia.desktop.app:v2021.7.2","resources":[{"_id":"req_db2c06f195b54d8f918af459e789c153","parentId":"fld_db4988d92bee489b97314a2c42912b44","modified":1644986538425,"created":1644831777188,"url":"http://localhost:5000/users/","name":"Create","description":"","method":"POST","body":{"mimeType":"application/json","text":"{\n \"addressId\": \"775\", \n \"fName\": \"Devin\", \n \"lName\": \"Brueberg\", \n \"userEmail\": \"brueberd@csp.edu\"\n}"},"parameters":[],"headers":[{"name":"Content-Type","value":"application/json","id":"pair_9d48c096793c44fca563aea569483650"}],"authentication":{},"metaSortKey":-1644927740008.25,"isPrivate":false,"settingStoreCookies":true,"settingSendCookies":true,"settingDisableRenderRequestBody":false,"settingEncodeUrl":true,"settingRebuildPath":false,"settingFollowRedirects":"global","_type":"request"},{"_id":"fld_db4988d92bee489b97314a2c42912b44","parentId":"fld_442777c22af6479484cfc6e8d7cc54d4","modified":1644962334426,"created":1644962334426,"name":"User","description":"","environment":{},"environmentPropertyOrder":null,"metaSortKey":-1644962334426,"_type":"request_group"},{"_id":"fld_442777c22af6479484cfc6e8d7cc54d4","parentId":"wrk_d7592aaa697642658cab14f4a4d8d660","modified":1644831666210,"created":1644831658169,"name":"Backend V2","description":"","environment":{},"environmentPropertyOrder":null,"metaSortKey":-1644823956005,"_type":"request_group"},{"_id":"wrk_d7592aaa697642658cab14f4a4d8d660","parentId":null,"modified":1642402196509,"created":1642402196509,"name":"My Collection","description":"","scope":"collection","_type":"workspace"},{"_id":"req_898c971c060f470fa897ae82085eb574","parentId":"fld_db4988d92bee489b97314a2c42912b44","modified":1644989779927,"created":1644969284247,"url":"http://localhost:5000/users/adduser","name":"Create User and Authentication Entries","description":"","method":"POST","body":{"mimeType":"application/json","text":"{\n \"addressId\": \"234\", \n \"fName\": \"apples\", \n \"lName\": \"apples\",  \n \"userEmail\": \"apples\", \n \"permissionId\": \"234\", \n \"userName\": \"apples\", \n \"userPassword\": \"apples\", \n \"historyId\": \"234\"  \n}"},"parameters":[],"headers":[{"name":"Content-Type","value":"application/json","id":"pair_9d48c096793c44fca563aea569483650"}],"authentication":{},"metaSortKey":-1644927739983.25,"isPrivate":false,"settingStoreCookies":true,"settingSendCookies":true,"settingDisableRenderRequestBody":false,"settingEncodeUrl":true,"settingRebuildPath":false,"settingFollowRedirects":"global","_type":"request"},{"_id":"req_f9fc34baff1a426893d3af0d84ed9b5b","parentId":"fld_db4988d92bee489b97314a2c42912b44","modified":1644989780348,"created":1644988791314,"url":"http://localhost:5000/users/adduser","name":"Create User, Auth, and Address","description":"","method":"POST","body":{"mimeType":"application/json","text":"{\n \"address\": \"1742 Evergreen Terrace\", \n \"city\": \"Springfield\", \n \"state\": \"MN\",\n \"zip\": \"90210\", \n \"fName\": \"apples\", \n \"lName\": \"apples\",  \n \"userEmail\": \"apples\", \n \"permissionId\": \"234\", \n \"userName\": \"apples\", \n \"userPassword\": \"apples\", \n \"historyId\": \"234\"  \n}"},"parameters":[],"headers":[{"name":"Content-Type","value":"application/json","id":"pair_9d48c096793c44fca563aea569483650"}],"authentication":{},"metaSortKey":-1644927739970.75,"isPrivate":false,"settingStoreCookies":true,"settingSendCookies":true,"settingDisableRenderRequestBody":false,"settingEncodeUrl":true,"settingRebuildPath":false,"settingFollowRedirects":"global","_type":"request"},{"_id":"req_8c66e6e526fc4ccaaf3326538cb3e5c9","parentId":"fld_db4988d92bee489b97314a2c42912b44","modified":1644967515671,"created":1644831676960,"url":"http://localhost:5000/users/","name":"Read All","description":"","method":"GET","body":{},"parameters":[],"headers":[],"authentication":{},"metaSortKey":-1644927739958.25,"isPrivate":false,"settingStoreCookies":true,"settingSendCookies":true,"settingDisableRenderRequestBody":false,"settingEncodeUrl":true,"settingRebuildPath":false,"settingFollowRedirects":"global","_type":"request"},{"_id":"req_0190d22a1c394c169c7f596bcc067146","parentId":"fld_db4988d92bee489b97314a2c42912b44","modified":1644984191449,"created":1644831755797,"url":"http://localhost:5000/users/2","name":"Read by ID","description":"","method":"GET","body":{},"parameters":[],"headers":[],"authentication":{},"metaSortKey":-1644927739933.25,"isPrivate":false,"settingStoreCookies":true,"settingSendCookies":true,"settingDisableRenderRequestBody":false,"settingEncodeUrl":true,"settingRebuildPath":false,"settingFollowRedirects":"global","_type":"request"},{"_id":"req_6bc0fbcd409d4f2b815970e3b83ee28b","parentId":"fld_db4988d92bee489b97314a2c42912b44","modified":1644968252385,"created":1644832357437,"url":"http://localhost:5000/users/23","name":"Update by ID","description":"","method":"PUT","body":{"mimeType":"application/json","text":"{\n \"addressId\": \"234\", \n \"fName\": \"Cole\", \n \"lName\": \"Diet\", \n \"userEmail\": \"coled@restaurantclub.net\"\n}"},"parameters":[],"headers":[{"name":"Content-Type","value":"application/json","id":"pair_f9af7e1f445b4336a3d369dca3c44325"}],"authentication":{},"metaSortKey":-1644927739883.25,"isPrivate":false,"settingStoreCookies":true,"settingSendCookies":true,"settingDisableRenderRequestBody":false,"settingEncodeUrl":true,"settingRebuildPath":true,"settingFollowRedirects":"global","_type":"request"},{"_id":"req_48e39c5fc08d4f49b70d23e8b1c1cb42","parentId":"fld_db4988d92bee489b97314a2c42912b44","modified":1644967541355,"created":1644831965448,"url":"http://localhost:5000/users/19","name":"Delete by ID","description":"","method":"DELETE","body":{},"parameters":[],"headers":[],"authentication":{},"metaSortKey":-1644927739833.25,"isPrivate":false,"settingStoreCookies":true,"settingSendCookies":true,"settingDisableRenderRequestBody":false,"settingEncodeUrl":true,"settingRebuildPath":false,"settingFollowRedirects":"global","_type":"request"},{"_id":"req_32e6695cb3e743e1b1860655b875f57d","parentId":"fld_c8633ec4ca934c3d9dfa934f7a743eb9","modified":1644987839436,"created":1644962386503,"url":"http://localhost:5000/authentication/","name":"Create","description":"","method":"POST","body":{"mimeType":"application/json","text":"{\n \"userId\": \"2\", \n \"permissionId\": \"3\", \n \"userName\": \"tacoman\", \n \"userPassword\": \"34566dfgsd\",\n \"historyId\": \"123\" \n}"},"parameters":[],"headers":[{"name":"Content-Type","value":"application/json","id":"pair_9d48c096793c44fca563aea569483650"}],"authentication":{},"metaSortKey":-1644927740008.25,"isPrivate":false,"settingStoreCookies":true,"settingSendCookies":true,"settingDisableRenderRequestBody":false,"settingEncodeUrl":true,"settingRebuildPath":false,"settingFollowRedirects":"global","_type":"request"},{"_id":"fld_c8633ec4ca934c3d9dfa934f7a743eb9","parentId":"fld_442777c22af6479484cfc6e8d7cc54d4","modified":1644962386499,"created":1644962386499,"name":"Authnentication","description":"","environment":{},"environmentPropertyOrder":null,"metaSortKey":-1644893145215.5,"_type":"request_group"},{"_id":"req_10e346fedb59403fb0ab964c99ac9255","parentId":"fld_c8633ec4ca934c3d9dfa934f7a743eb9","modified":1644967481190,"created":1644962386500,"url":"http://localhost:5000/authentication/","name":"Read All","description":"","method":"GET","body":{},"parameters":[],"headers":[],"authentication":{},"metaSortKey":-1644927739958.25,"isPrivate":false,"settingStoreCookies":true,"settingSendCookies":true,"settingDisableRenderRequestBody":false,"settingEncodeUrl":true,"settingRebuildPath":false,"settingFollowRedirects":"global","_type":"request"},{"_id":"req_7210ef303f73427c9d54f4cde6462415","parentId":"fld_c8633ec4ca934c3d9dfa934f7a743eb9","modified":1644967488258,"created":1644962386502,"url":"http://localhost:5000/authentication/12","name":"Read by ID","description":"","method":"GET","body":{},"parameters":[],"headers":[],"authentication":{},"metaSortKey":-1644927739933.25,"isPrivate":false,"settingStoreCookies":true,"settingSendCookies":true,"settingDisableRenderRequestBody":false,"settingEncodeUrl":true,"settingRebuildPath":false,"settingFollowRedirects":"global","_type":"request"},{"_id":"req_a166ba54c9c24180b84550a4c60d90f4","parentId":"fld_c8633ec4ca934c3d9dfa934f7a743eb9","modified":1644968255935,"created":1644962386506,"url":"http://localhost:5000/authentication/1","name":"Update by ID","description":"","method":"PUT","body":{"mimeType":"application/json","text":"{\n \"userId\": \"1\", \n \"permissionId\": \"1\", \n \"userName\": \"1\", \n \"userPassword\": \"1\",\n \"historyId\": \"1\" \n}"},"parameters":[],"headers":[{"name":"Content-Type","value":"application/json","id":"pair_f9af7e1f445b4336a3d369dca3c44325"}],"authentication":{},"metaSortKey":-1644927739883.25,"isPrivate":false,"settingStoreCookies":true,"settingSendCookies":true,"settingDisableRenderRequestBody":false,"settingEncodeUrl":true,"settingRebuildPath":true,"settingFollowRedirects":"global","_type":"request"},{"_id":"req_fd588141b28540f6818775df88c268a9","parentId":"fld_c8633ec4ca934c3d9dfa934f7a743eb9","modified":1644968096307,"created":1644962386505,"url":"http://localhost:5000/authentication/1","name":"Delete by ID","description":"","method":"DELETE","body":{},"parameters":[],"headers":[],"authentication":{},"metaSortKey":-1644927739833.25,"isPrivate":false,"settingStoreCookies":true,"settingSendCookies":true,"settingDisableRenderRequestBody":false,"settingEncodeUrl":true,"settingRebuildPath":false,"settingFollowRedirects":"global","_type":"request"},{"_id":"req_9178c324315a479db9bf4989a918845e","parentId":"fld_b2b1b8dccf854937bcc0a319a0d58716","modified":1644989205805,"created":1644967417662,"url":"http://localhost:5000/address/","name":"Create","description":"","method":"POST","body":{"mimeType":"application/json","text":"{\n \"address\": \"1742 Evergreen Terrace\", \n \"city\": \"Springfield\", \n \"state\": \"MN\",\n \"zip\": \"90210\" \n}"},"parameters":[],"headers":[{"name":"Content-Type","value":"application/json","id":"pair_9d48c096793c44fca563aea569483650"}],"authentication":{},"metaSortKey":-1644927740008.25,"isPrivate":false,"settingStoreCookies":true,"settingSendCookies":true,"settingDisableRenderRequestBody":false,"settingEncodeUrl":true,"settingRebuildPath":false,"settingFollowRedirects":"global","_type":"request"},{"_id":"fld_b2b1b8dccf854937bcc0a319a0d58716","parentId":"fld_442777c22af6479484cfc6e8d7cc54d4","modified":1644967417657,"created":1644967417657,"name":"Address","description":"","environment":{},"environmentPropertyOrder":null,"metaSortKey":-1644858550610.25,"_type":"request_group"},{"_id":"req_85e3a45860ec4e1a9d8e04930a6b42ab","parentId":"fld_b2b1b8dccf854937bcc0a319a0d58716","modified":1644967559573,"created":1644967417659,"url":"http://localhost:5000/address/","name":"Read All","description":"","method":"GET","body":{},"parameters":[],"headers":[],"authentication":{},"metaSortKey":-1644927739958.25,"isPrivate":false,"settingStoreCookies":true,"settingSendCookies":true,"settingDisableRenderRequestBody":false,"settingEncodeUrl":true,"settingRebuildPath":false,"settingFollowRedirects":"global","_type":"request"},{"_id":"req_0fde7541e09d4aa38af8eaf46f226095","parentId":"fld_b2b1b8dccf854937bcc0a319a0d58716","modified":1644967852874,"created":1644967417660,"url":"http://localhost:5000/address/1","name":"Read by ID","description":"","method":"GET","body":{},"parameters":[],"headers":[],"authentication":{},"metaSortKey":-1644927739933.25,"isPrivate":false,"settingStoreCookies":true,"settingSendCookies":true,"settingDisableRenderRequestBody":false,"settingEncodeUrl":true,"settingRebuildPath":false,"settingFollowRedirects":"global","_type":"request"},{"_id":"req_18506ea0b7aa4947885feff41787437c","parentId":"fld_b2b1b8dccf854937bcc0a319a0d58716","modified":1644987980775,"created":1644967417665,"url":"http://localhost:5000/address/2","name":"Update by ID","description":"","method":"PUT","body":{"mimeType":"application/json","text":"{\n \"address\": \"1\", \n \"city\": \"1\", \n \"state\": \"1\",\n \"zip\": \"1\" \n}"},"parameters":[],"headers":[{"name":"Content-Type","value":"application/json","id":"pair_f9af7e1f445b4336a3d369dca3c44325"}],"authentication":{},"metaSortKey":-1644927739883.25,"isPrivate":false,"settingStoreCookies":true,"settingSendCookies":true,"settingDisableRenderRequestBody":false,"settingEncodeUrl":true,"settingRebuildPath":true,"settingFollowRedirects":"global","_type":"request"},{"_id":"req_fb1c5359e6494c0594ab337b8ca17e9f","parentId":"fld_b2b1b8dccf854937bcc0a319a0d58716","modified":1644968287295,"created":1644967417663,"url":"http://localhost:5000/address/1","name":"Delete by ID","description":"","method":"DELETE","body":{},"parameters":[],"headers":[],"authentication":{},"metaSortKey":-1644927739833.25,"isPrivate":false,"settingStoreCookies":true,"settingSendCookies":true,"settingDisableRenderRequestBody":false,"settingEncodeUrl":true,"settingRebuildPath":false,"settingFollowRedirects":"global","_type":"request"},{"_id":"req_38cba02e812340acbbda614301ca0711","parentId":"fld_19ea64e8684b48d287375337df973781","modified":1644971500216,"created":1644971485090,"url":"http://localhost:5000/history/","name":"Create","description":"","method":"POST","body":{"mimeType":"application/json","text":"{\n \"userId\": \"775\", \n \"address\": \"1742 Evergreen Terrace\", \n \"city\": \"Springfield\", \n \"state\": \"MN\",\n \"zip\": \"90210\" \n}"},"parameters":[],"headers":[{"name":"Content-Type","value":"application/json","id":"pair_9d48c096793c44fca563aea569483650"}],"authentication":{},"metaSortKey":-1644927740008.25,"isPrivate":false,"settingStoreCookies":true,"settingSendCookies":true,"settingDisableRenderRequestBody":false,"settingEncodeUrl":true,"settingRebuildPath":false,"settingFollowRedirects":"global","_type":"request"},{"_id":"fld_19ea64e8684b48d287375337df973781","parentId":"fld_442777c22af6479484cfc6e8d7cc54d4","modified":1644971485086,"created":1644971485086,"name":"History","description":"","environment":{},"environmentPropertyOrder":null,"metaSortKey":-1644841253307.625,"_type":"request_group"},{"_id":"req_d7891a5b589c43ffa09a7b9afe2b00ea","parentId":"fld_19ea64e8684b48d287375337df973781","modified":1644971485087,"created":1644971485087,"url":"http://localhost:5000/address/","name":"Read All","description":"","method":"GET","body":{},"parameters":[],"headers":[],"authentication":{},"metaSortKey":-1644927739958.25,"isPrivate":false,"settingStoreCookies":true,"settingSendCookies":true,"settingDisableRenderRequestBody":false,"settingEncodeUrl":true,"settingRebuildPath":false,"settingFollowRedirects":"global","_type":"request"},{"_id":"req_a2bf53f2a6004393a0b69755e43a162e","parentId":"fld_19ea64e8684b48d287375337df973781","modified":1644971485089,"created":1644971485089,"url":"http://localhost:5000/address/1","name":"Read by ID","description":"","method":"GET","body":{},"parameters":[],"headers":[],"authentication":{},"metaSortKey":-1644927739933.25,"isPrivate":false,"settingStoreCookies":true,"settingSendCookies":true,"settingDisableRenderRequestBody":false,"settingEncodeUrl":true,"settingRebuildPath":false,"settingFollowRedirects":"global","_type":"request"},{"_id":"req_4397ddba919a435ea85bb32f5d9a170a","parentId":"fld_19ea64e8684b48d287375337df973781","modified":1644971485093,"created":1644971485093,"url":"http://localhost:5000/address/2","name":"Update by ID","description":"","method":"PUT","body":{"mimeType":"application/json","text":"{\n \"userId\": \"1\", \n \"address\": \"1\", \n \"city\": \"1\", \n \"state\": \"1\",\n \"zip\": \"1\" \n}"},"parameters":[],"headers":[{"name":"Content-Type","value":"application/json","id":"pair_f9af7e1f445b4336a3d369dca3c44325"}],"authentication":{},"metaSortKey":-1644927739883.25,"isPrivate":false,"settingStoreCookies":true,"settingSendCookies":true,"settingDisableRenderRequestBody":false,"settingEncodeUrl":true,"settingRebuildPath":true,"settingFollowRedirects":"global","_type":"request"},{"_id":"req_515d0893ba1149db8de4f95f5eb50bd4","parentId":"fld_19ea64e8684b48d287375337df973781","modified":1644971485092,"created":1644971485092,"url":"http://localhost:5000/address/1","name":"Delete by ID","description":"","method":"DELETE","body":{},"parameters":[],"headers":[],"authentication":{},"metaSortKey":-1644927739833.25,"isPrivate":false,"settingStoreCookies":true,"settingSendCookies":true,"settingDisableRenderRequestBody":false,"settingEncodeUrl":true,"settingRebuildPath":false,"settingFollowRedirects":"global","_type":"request"},{"_id":"env_c199eea7cd6fdeea8cef0ea3029542d73b046d5e","parentId":"wrk_d7592aaa697642658cab14f4a4d8d660","modified":1642404248645,"created":1642402196512,"name":"Base Environment","data":{},"dataPropertyOrder":{},"color":null,"isPrivate":false,"metaSortKey":1642402196512,"_type":"environment"},{"_id":"jar_c199eea7cd6fdeea8cef0ea3029542d73b046d5e","parentId":"wrk_d7592aaa697642658cab14f4a4d8d660","modified":1642402196513,"created":1642402196513,"name":"Default Jar","cookies":[],"_type":"cookie_jar"},{"_id":"spc_a541811cd6c946d6938c5706cc01b848","parentId":"wrk_d7592aaa697642658cab14f4a4d8d660","modified":1642402196510,"created":1642402196510,"fileName":"My Collection","contents":"","contentType":"yaml","_type":"api_spec"}]}